[{"url":"/weibo?q=%23%E4%BD%9B%E5%BE%97%E8%A7%92%E9%97%A8%E5%B0%86%E6%B6%A8%E7%B2%89%E6%96%AD%E5%B1%82%E7%AC%AC%E4%B8%80%23","text":"佛得角门将涨粉断层第一","count":779308,"firstSeen":"2026-07-13T11:11:22.996Z","peakCount":779308,"prevCount":0,"velocity":100,"status":"new","textEn":"Cape Verde goalkeeper ranks first in popularity"},{"url":"/weibo?q=%23%E6%B2%88%E9%98%B3%E6%9A%B4%E9%9B%A8%E4%B8%80%E7%94%B7%E5%AD%90%E5%80%92%E7%A7%AF%E6%B0%B4%E4%B8%AD%23","text":"沈阳暴雨一男子倒积水中","count":556699,"firstSeen":"2026-07-13T11:11:22.996Z","peakCount":556699,"prevCount":0,"velocity":100,"status":"new"},{"url":"/weibo?q=%23%E4%B8%9C%E5%8C%97%E7%89%B9%E5%A4%A7%E6%9A%B4%E9%9B%A8%23","text":"东北特大暴雨","count":398203,"firstSeen":"2026-07-13T11:11:22.996Z","peakCount":398203,"prevCount":0,"velocity":100,"status":"new"},{"url":"/weibo?q=%23%E5%8E%9F%E6%9D%A5%E5%B7%B2%E8%AF%BB%E4%B8%8D%E5%9B%9E%E7%9A%84%E4%BA%BA%E6%98%AF%E8%BF%99%E6%A0%B7%E6%83%B3%E7%9A%84%23","text":"原来已读不回的人是这样想的","count":397045,"firstSeen":"2026-07-13T11:11:22.996Z","peakCount":397045,"prevCount":0,"velocity":100,"status":"new"},{"url":"/weibo?q=%23%E9%95%BF%E6%9C%9F%E5%A4%A7%E9%87%8F%E9%98%85%E8%AF%BB%E7%9A%84%E5%A5%BD%E5%A4%84%23","text":"长期大量阅读的好处","count":388692,"firstSeen":"2026-07-13T11:11:22.996Z","peakCount":388692,"prevCount":0,"velocity":100,"status":"new"},{"url":"/weibo?q=%23%E7%BD%91%E4%BC%A0TF%E5%AE%B6%E6%97%8F%E8%BF%90%E5%8A%A8%E4%BC%9A%E5%88%86%E7%BB%84%23","text":"网传TF家族运动会分组","count":384572,"firstSeen":"2026-07-13T11:11:22.996Z","peakCount":384572,"prevCount":0,"velocity":100,"status":"new"},{"url":"/weibo?q=%23%E6%88%91%E5%9B%BD%E6%88%96%E8%BF%98%E5%B0%86%E9%81%AD%E9%81%872%E8%87%B33%E4%B8%AA%E5%8F%B0%E9%A3%8E%23","text":"我国或还将遭遇2至3个台风","count":379355,"firstSeen":"2026-07-13T11:11:22.996Z","peakCount":379355,"prevCount":0,"velocity":100,"status":"new"},{"url":"/weibo?q=%23%E8%AF%B4%E4%B8%80%E4%B8%AA%E5%87%8F%E8%82%A5%E7%9A%84%E5%86%B7%E7%9F%A5%E8%AF%86%23","text":"说一个减肥的冷知识","count":374364,"firstSeen":"2026-07-13T11:11:22.996Z","peakCount":374364,"prevCount":0,"velocity":100,"status":"new"},{"url":"/weibo?q=%23%E9%83%AD%E6%95%AC%E6%98%8E%E8%AE%A9%E8%89%BE%E7%B1%B3%E8%AE%B0%E5%BE%97%E5%87%8F%E8%82%A5%23","text":"郭敬明让艾米记得减肥","count":367143,"firstSeen":"2026-07-13T11:11:22.996Z","peakCount":367143,"prevCount":0,"velocity":100,"status":"new"},{"url":"/weibo?q=%23%E5%BC%A0%E5%A9%A7%E4%BB%AA%E5%BC%A0%E5%87%8C%E8%B5%AB%E5%85%B0%E8%94%BB%E5%8D%87Title%23","text":"张婧仪张凌赫兰蔻升Title","count":350198,"firstSeen":"2026-07-13T11:11:22.996Z","peakCount":350198,"prevCount":0,"velocity":100,"status":"new"},{"url":"/weibo?q=%23%E8%BE%BD%E5%AE%81%E6%9C%80%E5%A4%A7%E9%99%8D%E9%9B%A8%E9%87%8F%E5%9C%A8%E6%B2%88%E9%98%B3%23","text":"辽宁最大降雨量在沈阳","count":340218,"firstSeen":"2026-07-13T11:11:22.996Z","peakCount":340218,"prevCount":0,"velocity":100,"status":"new","textEn":"The highest rainfall in Liaoning is in Shenyang"},{"url":"/weibo?q=%23%E6%88%91%E4%BB%AC%E4%B8%BA%E4%BB%80%E4%B9%88%E8%A6%81%E8%83%8C%E6%9C%A8%E5%85%B0%E7%9A%84%E8%B4%AD%E4%B9%B0%E8%AE%B0%E5%BD%95%23","text":"我们为什么要背木兰的购买记录","count":337248,"firstSeen":"2026-07-13T11:11:22.996Z","peakCount":337248,"prevCount":0,"velocity":100,"status":"new"},{"url":"/weibo?q=%23%E9%A9%B0%E6%8F%B4%E5%B9%BF%E8%A5%BF%23","text":"驰援广西","count":328374,"firstSeen":"2026-07-13T11:11:22.996Z","peakCount":328374,"prevCount":0,"velocity":100,"status":"new"},{"url":"/weibo?q=%23%E4%B8%AD%E9%A4%90%E5%8E%85%20%E8%9B%8B%E7%B3%95%23","text":"中餐厅 蛋糕","count":327408,"firstSeen":"2026-07-13T11:11:22.996Z","peakCount":327408,"prevCount":0,"velocity":100,"status":"new"},{"url":"/weibo?q=%23%E9%95%BF%E9%91%AB%E8%BF%912%E4%B8%87%E5%91%98%E5%B7%A5%E6%AF%8F%E4%BA%BA%E5%8F%AF%E5%88%86%E8%B6%85%E7%99%BE%E4%B8%87%23","text":"长鑫近2万员工每人可分超百万","count":321653,"firstSeen":"2026-07-13T11:11:22.996Z","peakCount":321653,"prevCount":0,"velocity":100,"status":"new"},{"url":"/weibo?q=%23%E5%B0%8F%E5%A5%B3%E5%AD%A9%E4%B8%BA%E6%8A%97%E6%B4%AA%E6%88%98%E5%A3%AB%E9%80%92%E4%B8%8A%E6%B8%A9%E6%B0%B4%23","text":"小女孩为抗洪战士递上温水","count":321652,"firstSeen":"2026-07-13T11:11:22.996Z","peakCount":321652,"prevCount":0,"velocity":100,"status":"new"},{"url":"/weibo?q=%23%E5%AD%99%E9%A2%96%E8%8E%8E%E8%9C%A1%E5%83%8F%E8%BF%98%E5%8E%9F%E5%B0%8F%E8%85%BF%E6%B7%A4%E9%9D%92%23","text":"孙颖莎蜡像还原小腿淤青","count":321651,"firstSeen":"2026-07-13T11:11:22.996Z","peakCount":321651,"prevCount":0,"velocity":100,"status":"new"},{"url":"/weibo?q=%23%E8%89%BE%E7%B1%B3%E5%9B%A0%E4%B8%BA%E6%A1%A3%E6%9C%9F%E9%94%99%E8%BF%87%E6%9C%88%E9%B3%9E%E7%BB%AE%E7%BA%AA%23","text":"艾米因为档期错过月鳞绮纪","count":320992,"firstSeen":"2026-07-13T11:11:22.996Z","peakCount":320992,"prevCount":0,"velocity":100,"status":"new"},{"url":"/weibo?q=%23%E5%BC%A0%E9%9B%85%E7%90%AA%E7%8E%B0%E5%AE%9E%E7%89%88%E7%B4%AB%E8%96%AF%E7%B2%BE%23","text":"张雅琪现实版紫薯精","count":320056,"firstSeen":"2026-07-13T11:11:22.996Z","peakCount":320056,"prevCount":0,"velocity":100,"status":"new"},{"url":"/weibo?q=%23%E7%A7%9F%E5%AE%A2%E6%AC%A012.7%E4%B8%87%E7%A7%9F%E9%87%91%E8%BF%98%E6%8A%8A%E5%95%86%E9%93%BA%E8%BD%AC%E7%A7%9F%E4%BA%86%23","text":"租客欠12.7万租金还把商铺转租了","count":317464,"firstSeen":"2026-07-13T11:11:22.996Z","peakCount":317464,"prevCount":0,"velocity":100,"status":"new"},{"url":"/weibo?q=%23%E9%82%B9%E5%B8%82%E6%98%8E%E8%AE%A9%E6%88%91%E6%83%B3%E8%B5%B7%E9%83%91%E4%BC%8A%E5%81%A5%23","text":"邹市明让我想起郑伊健","count":316805,"firstSeen":"2026-07-13T11:11:22.996Z","peakCount":316805,"prevCount":0,"velocity":100,"status":"new","textEn":"Zou Shiming reminds me of Ekin Cheng"},{"url":"/weibo?q=%23%E6%97%A5%E6%9C%AC%E5%AE%A3%E5%B8%83%E5%8F%AF%E5%9B%9E%E6%94%B6%E7%81%AB%E7%AE%AD%E8%AF%95%E9%A3%9E%E6%88%90%E5%8A%9F%23","text":"日本宣布可回收火箭试飞成功","count":314626,"firstSeen":"2026-07-13T11:11:22.996Z","peakCount":314626,"prevCount":0,"velocity":100,"status":"new"},{"url":"/weibo?q=%23%E9%BB%84%E7%81%BF%E7%81%BF%E5%90%90%E6%A7%BD%E5%81%9A%E7%9A%84%E4%BA%94%E8%8A%B1%E8%82%89%E5%A5%BD%E9%9A%BE%E5%90%83%23","text":"黄灿灿吐槽做的五花肉好难吃","count":314222,"firstSeen":"2026-07-13T11:11:22.996Z","peakCount":314222,"prevCount":0,"velocity":100,"status":"new"},{"url":"/weibo?q=%23%E8%94%A1%E5%BE%90%E5%9D%A4%E6%BE%B3%E9%97%A8%E8%BF%9E%E5%BC%80%E4%B8%A4%E5%A4%A9%23","text":"蔡徐坤澳门连开两天","count":313384,"firstSeen":"2026-07-13T11:11:22.996Z","peakCount":313384,"prevCount":0,"velocity":100,"status":"new"},{"url":"/weibo?q=%23%E5%A5%B3%E8%A3%85%E8%83%BD%E4%B8%8D%E8%83%BD%E5%88%AB%E7%BB%99%E8%A1%A3%E6%9C%8D%E4%B9%B1%E8%B5%B7%E5%90%8D%E5%AD%97%E4%BA%86%23","text":"女装能不能别给衣服乱起名字了","count":291903,"firstSeen":"2026-07-13T11:11:22.996Z","peakCount":291903,"prevCount":0,"velocity":100,"status":"new"},{"url":"/weibo?q=%23%E5%88%98%E8%80%80%E6%96%87%E9%AB%98%E4%BC%9A%E7%9B%B4%E6%92%AD%23","text":"刘耀文高会直播","count":287123,"firstSeen":"2026-07-13T11:11:22.996Z","peakCount":287123,"prevCount":0,"velocity":100,"status":"new"},{"url":"/weibo?q=%23%E5%8A%9F%E5%A4%AB%E5%A5%B3%E8%B6%B3%E5%92%8C%E5%8A%9F%E5%A4%AB%E5%B7%AE%E4%BA%86%E5%8D%81%E4%B8%AA%E5%B0%91%E6%9E%97%E8%B6%B3%E7%90%83%23","text":"功夫女足和功夫差了十个少林足球","count":279836,"firstSeen":"2026-07-13T11:11:22.996Z","peakCount":279836,"prevCount":0,"velocity":100,"status":"new"},{"url":"/weibo?q=%23%E6%AF%95%E4%B8%9A%E6%97%85%E8%A1%8C%E7%9A%84%E8%BD%A6%E4%B8%8A%E4%BD%A0%E4%BB%AC%E5%9C%A8%E5%BE%AA%E7%8E%AF%E5%93%AA%E9%A6%96%E6%AD%8C%23","text":"毕业旅行的车上你们在循环哪首歌","count":249316,"firstSeen":"2026-07-13T11:11:22.996Z","peakCount":249316,"prevCount":0,"velocity":100,"status":"new"},{"url":"/weibo?q=%23%E8%BF%AA%E4%B8%BD%E7%83%AD%E5%B7%B4%E6%9D%A8%E6%B4%8B%E8%BF%8E%E6%9D%A5%E4%BA%86%E6%9C%80%E9%80%82%E9%85%8D%E7%9A%84bgm%23","text":"迪丽热巴杨洋迎来了最适配的bgm","count":241058,"firstSeen":"2026-07-13T11:11:22.996Z","peakCount":241058,"prevCount":0,"velocity":100,"status":"new"},{"url":"/weibo?q=%23%E5%A4%A9%E6%B4%A5%E5%B9%BF%E7%94%B5%23","text":"天津广电","count":238736,"firstSeen":"2026-07-13T11:11:22.996Z","peakCount":238736,"prevCount":0,"velocity":100,"status":"new"},{"url":"/weibo?q=%23%E8%BF%99%E4%B8%AA%E4%B8%96%E7%95%8C%E4%B8%8A%E4%B8%BA%E4%BB%80%E4%B9%88%E6%B2%A1%E6%9C%89%E6%8B%BC%E7%8F%AD%E5%95%8A%23","text":"这个世界上为什么没有拼班啊","count":237651,"firstSeen":"2026-07-13T11:11:22.996Z","peakCount":237651,"prevCount":0,"velocity":100,"status":"new","textEn":"Why is there no joint class in this world?"},{"url":"/weibo?q=%23%E6%B2%88%E9%98%B3%E6%9A%B4%E9%9B%A8%E7%8E%B0%E5%9C%BA%E7%94%BB%E9%9D%A2%23","text":"沈阳暴雨现场画面","count":236955,"firstSeen":"2026-07-13T11:11:22.996Z","peakCount":236955,"prevCount":0,"velocity":100,"status":"new"},{"url":"/weibo?q=%23%E5%AE%8B%E5%A8%81%E9%BE%99%E6%96%87%E6%A1%88%23","text":"宋威龙文案","count":236858,"firstSeen":"2026-07-13T11:11:22.996Z","peakCount":236858,"prevCount":0,"velocity":100,"status":"new"},{"url":"/weibo?q=%23%E5%85%B6%E5%AE%9E%E7%9D%A1%E8%A1%A3%E5%BA%94%E8%AF%A5%E5%8F%8D%E8%BF%87%E6%9D%A5%E7%A9%BF%23","text":"其实睡衣应该反过来穿","count":236637,"firstSeen":"2026-07-13T11:11:22.996Z","peakCount":236637,"prevCount":0,"velocity":100,"status":"new"},{"url":"/weibo?q=%23papi%E9%85%B1%E5%9B%A2%E9%98%9F%E7%A8%B3%E5%AE%9A%E6%80%A7%23","text":"papi酱团队稳定性","count":233451,"firstSeen":"2026-07-13T11:11:22.996Z","peakCount":233451,"prevCount":0,"velocity":100,"status":"new"},{"url":"/weibo?q=%23A%E8%82%A1%E5%AD%98%E5%82%A8%E4%B8%80%E5%93%A5%E5%9B%9E%E5%BA%94%E8%B7%8C%E5%81%9C%23","text":"A股存储一哥回应跌停","count":232041,"firstSeen":"2026-07-13T11:11:22.996Z","peakCount":232041,"prevCount":0,"velocity":100,"status":"new"},{"url":"/weibo?q=%23%E4%B8%AD%E9%A4%90%E5%8E%85%E6%96%B0%E7%9A%84%E6%98%8E%E5%AD%A6%E7%BB%A7%E6%89%BF%E4%BA%BA%23","text":"中餐厅新的明学继承人","count":230084,"firstSeen":"2026-07-13T11:11:22.996Z","peakCount":230084,"prevCount":0,"velocity":100,"status":"new"},{"url":"/weibo?q=%23%E5%AE%8B%E6%85%A7%E4%B9%94%20%E8%B6%8A%E7%B4%A0%E8%B6%8A%E7%BE%8E%23","text":"宋慧乔 越素越美","count":227607,"firstSeen":"2026-07-13T11:11:22.996Z","peakCount":227607,"prevCount":0,"velocity":100,"status":"new"},{"url":"/weibo?q=%23%E6%88%91%E7%9A%84codex%E6%8A%8A%E8%87%AA%E5%B7%B1%E5%8D%B8%E8%BD%BD%E4%BA%86%23","text":"我的codex把自己卸载了","count":226423,"firstSeen":"2026-07-13T11:11:22.996Z","peakCount":226423,"prevCount":0,"velocity":100,"status":"new"},{"url":"/weibo?q=%23%E6%95%A3%E4%BC%99%E9%A5%AD%E4%B8%80%E6%94%BE%E8%BF%99%E9%A6%96%E6%88%91%E7%9B%B4%E6%8E%A5%E7%A0%B4%E9%98%B2%23","text":"散伙饭一放这首我直接破防","count":226222,"firstSeen":"2026-07-13T11:11:22.996Z","peakCount":226222,"prevCount":0,"velocity":100,"status":"new"},{"url":"/weibo?q=%23%E6%9A%B4%E9%9B%A8%E5%86%85%E6%B6%9D%E9%81%BF%E9%99%A9%E6%95%99%E7%A8%8B%23","text":"暴雨内涝避险教程","count":643593,"textEn":"Heavy rain and waterlogging avoidance tutorial","firstSeen":"2026-07-13T07:54:54.039Z","peakCount":643593,"prevCount":236695,"velocity":172,"status":"rising"},{"url":"/weibo?q=%23%E5%8F%B0%E7%A7%AF%E7%94%B52nm%E8%8A%AF%E7%89%87%E5%BC%80%E5%A7%8B%E9%87%8F%E4%BA%A7%23","text":"台积电2nm芯片开始量产","count":321653,"firstSeen":"2026-07-13T07:54:54.039Z","peakCount":321653,"prevCount":237135,"velocity":36,"status":"rising"},{"url":"/weibo?q=%23%E4%B8%AD%E5%9B%BD%E9%A6%96%E4%B8%AA%E7%A6%81%E5%94%AE%E7%87%83%E6%B2%B9%E8%BD%A6%E7%9C%81%E4%BB%BD%E7%A1%AE%E8%AE%A4%23","text":"中国首个禁售燃油车省份确认","count":1111055,"textEn":"China's first province to ban sales of fuel vehicles confirmed","firstSeen":"2026-07-13T07:54:54.039Z","peakCount":1996670,"prevCount":1996670,"velocity":-44,"status":"falling"},{"url":"/weibo?q=%23%E4%B8%AD%E9%A4%90%E5%8E%85%20%E5%BC%A0%E9%9B%85%E7%90%AA%23","text":"中餐厅 张雅琪","count":361803,"firstSeen":"2026-07-13T07:54:54.039Z","peakCount":1261873,"prevCount":1261873,"velocity":-71,"status":"falling"},{"url":"/weibo?q=%23%E6%B2%88%E9%98%B3%E7%99%BE%E5%B9%B4%E4%B8%80%E9%81%87%E6%9A%B4%E9%9B%A8%23","text":"沈阳百年一遇暴雨","count":355896,"firstSeen":"2026-07-13T07:54:54.039Z","peakCount":578972,"prevCount":578972,"velocity":-39,"status":"falling"},{"url":"/weibo?q=%23iPhone20%E5%86%8D%E6%9B%9D%E5%85%89%23","text":"iPhone20再曝光","count":319447,"firstSeen":"2026-07-13T07:54:54.039Z","peakCount":1039562,"prevCount":1039562,"velocity":-69,"status":"falling"},{"url":"/weibo?q=%23%E6%9B%9D%E6%9D%8E%E5%B0%8F%E5%86%89%E5%BE%90%E4%BD%B3%E5%AE%81%E7%A6%BB%E5%A9%9A%23","text":"曝李小冉徐佳宁离婚","count":318585,"firstSeen":"2026-07-13T04:41:58.443Z","peakCount":740921,"prevCount":740921,"velocity":-57,"status":"falling"},{"url":"/weibo?q=%23%E5%AD%9F%E5%AD%90%E4%B9%89%E9%BA%A6%E7%B2%92%E8%82%BF%E5%8F%AA%E9%9C%B2%E5%8D%8A%E8%BE%B9%E8%84%B8%23","text":"孟子义麦粒肿只露半边脸","count":315808,"textEn":"Meng Ziyi’s stye only shows half of his face","firstSeen":"2026-07-13T07:54:54.039Z","peakCount":737131,"prevCount":737131,"velocity":-57,"status":"falling"},{"url":"/weibo?q=%23%E6%B6%88%E8%B4%B9%E8%A7%82%E7%AA%81%E7%84%B6%E5%B0%B1%E8%A2%AB%E7%9F%AB%E6%AD%A3%E4%BA%86%23","text":"消费观突然就被矫正了","count":312709,"firstSeen":"2026-07-13T07:54:54.039Z","peakCount":1261780,"prevCount":1261780,"velocity":-75,"status":"falling"},{"url":"/weibo?q=%2317%E5%A4%A9%E6%96%B0%E7%94%9F%E5%84%BF%E8%A2%AB%E8%87%AA%E5%AE%B6%E5%AE%A0%E7%89%A9%E7%8B%97%E5%92%AC%E5%BC%80%E8%84%91%E8%A2%8B%23","text":"17天新生儿被自家宠物狗咬开脑袋","count":308565,"firstSeen":"2026-07-13T07:54:54.039Z","peakCount":739169,"prevCount":739169,"velocity":-58,"status":"falling"},{"url":"/weibo?q=%23%E9%9D%92%E5%B2%9B%20%E6%B5%B7%E6%B0%B4%E5%80%92%E7%81%8C%23","text":"青岛 海水倒灌","count":1266290,"firstSeen":"2026-07-13T07:54:54.039Z","peakCount":1266290,"prevCount":1266290,"velocity":-100,"status":"gone"},{"url":"/weibo?q=%23%E4%B8%A5%E6%89%93%E7%BC%96%E9%80%A0%E4%BC%A0%E6%92%AD%E6%B6%89%E6%B1%9B%E7%AD%89%E6%B6%89%E7%81%BE%E7%BD%91%E7%BB%9C%E8%B0%A3%E8%A8%80%23","text":"严打编造传播涉汛等涉灾网络谣言","count":1261902,"firstSeen":"2026-07-13T07:54:54.039Z","peakCount":1261902,"prevCount":1261902,"velocity":-100,"status":"gone"},{"url":"/weibo?q=%23%E6%9C%8B%E5%8F%8B%E5%9C%88%E7%9A%84%E5%A4%A7%E5%AE%B6%E5%A5%BD%E5%83%8F%E9%83%BD%E5%A4%B1%E5%8E%BB%E4%BA%86%E7%81%B5%E6%B0%94%23","text":"朋友圈的大家好像都失去了灵气","count":1261899,"firstSeen":"2026-07-13T07:54:54.039Z","peakCount":1261899,"prevCount":1261899,"velocity":-100,"status":"gone","textEn":"Everyone in the circle of friends seems to have lost their aura"},{"url":"/weibo?q=%23%E6%96%B0%E8%83%BD%E6%BA%90%E8%BD%A6%E4%B8%BB3%E8%87%B35%E5%B9%B4%E5%B0%B1%E8%A6%81%E6%8D%A2%E8%BD%A6%23","text":"新能源车主3至5年就要换车","count":1169607,"firstSeen":"2026-07-13T01:05:14.811Z","peakCount":1169607,"prevCount":1169607,"velocity":-100,"status":"gone"},{"url":"/weibo?q=%23%E5%A4%8F%E7%B2%AE%E5%A2%9E%E4%BA%A720%E4%BA%BF%E6%96%A4%E8%83%8C%E5%90%8E%E7%9A%84%E7%A7%91%E6%8A%80%E5%AF%86%E7%A0%81%23","text":"夏粮增产20亿斤背后的科技密码","count":1132904,"textEn":"The scientific and technological code behind increasing summer grain production by 2 billion jin","firstSeen":"2026-07-12T22:24:55.538Z","peakCount":1132904,"prevCount":1132904,"velocity":-100,"status":"gone"},{"url":"/weibo?q=%23%E6%8E%A5%E8%B0%81%E7%9A%84%E5%AD%A9%E5%AD%90%E4%B8%8D%E6%98%AF%E6%8E%A5%23","text":"接谁的孩子不是接","count":974057,"firstSeen":"2026-07-13T07:54:54.039Z","peakCount":974057,"prevCount":974057,"velocity":-100,"status":"gone"},{"url":"/weibo?q=%23%E5%B7%B4%E5%A8%81%E6%98%8E%E5%A4%A9%E5%85%A5%E6%B5%B7%23","text":"巴威明天入海","count":914969,"firstSeen":"2026-07-13T01:05:14.811Z","peakCount":1105089,"prevCount":914969,"velocity":-100,"status":"gone","textEn":"Bawei will enter the sea tomorrow"},{"url":"/weibo?q=%23%E8%BF%99%E6%B3%A2%E4%B8%AD%E5%9B%BD%E5%88%B6%E9%80%A0%E5%A4%AA%E6%8F%90%E6%B0%94%23","text":"这波中国制造太提气","count":909577,"firstSeen":"2026-07-13T04:41:58.443Z","peakCount":909577,"prevCount":909577,"velocity":-100,"status":"gone"},{"url":"/weibo?q=%23%E7%9C%9F%E7%9A%84%E5%BE%88%E5%96%9C%E6%AC%A200%E5%90%8E%E7%9A%84%E5%B7%A5%E4%BD%9C%E6%80%81%E5%BA%A6%23","text":"真的很喜欢00后的工作态度","count":866952,"firstSeen":"2026-07-13T04:41:58.443Z","peakCount":866952,"prevCount":866952,"velocity":-100,"status":"gone"},{"url":"/weibo?q=%23%E5%9B%BD%E4%BA%A7%E5%8A%A8%E5%8A%9B%E8%88%9F%E6%A1%A5%E6%8A%97%E6%B4%AA%E6%9C%89%E5%A4%9A%E7%A1%AC%E6%A0%B8%23","text":"国产动力舟桥抗洪有多硬核","count":851203,"firstSeen":"2026-07-12T16:29:39.620Z","peakCount":851203,"prevCount":851203,"velocity":-100,"status":"gone","textEn":"How hard is the domestic power boat bridge to resist floods?"},{"url":"/weibo?q=%23%E9%98%BF%E6%A0%B9%E5%BB%B7%E7%94%B3%E8%AF%B7%E5%8D%8A%E5%86%B3%E8%B5%9B%E7%A9%BF%E5%AE%A2%E5%9C%BA%E9%98%9F%E6%9C%8D%23","text":"阿根廷申请半决赛穿客场队服","count":769158,"textEn":"Argentina applies to wear away jersey in semi-finals","firstSeen":"2026-07-13T04:41:58.443Z","peakCount":1896890,"prevCount":769158,"velocity":-100,"status":"gone"},{"url":"/weibo?q=%23%E9%87%8E%E7%8B%97%E9%AA%A8%E5%A4%B4%E7%AC%AC17%E9%9B%86%E5%B0%81%E7%A5%9E%23","text":"野狗骨头第17集封神","count":741421,"firstSeen":"2026-07-13T07:54:54.039Z","peakCount":741421,"prevCount":741421,"velocity":-100,"status":"gone"},{"url":"/weibo?q=%23%E5%B7%B4%E5%A8%81%E8%BF%98%E6%B2%A1%E8%B5%B0%E6%B5%B7%E7%A5%9E%E5%B0%B1%E8%A6%81%E6%9D%A5%E4%BA%86%23","text":"巴威还没走海神就要来了","count":568692,"firstSeen":"2026-07-13T07:54:54.039Z","peakCount":568692,"prevCount":568692,"velocity":-100,"status":"gone"},{"url":"/weibo?q=%23Bin%E6%95%B0%E6%8D%AE%E5%85%AC%E5%B8%83%23","text":"Bin数据公布","count":527265,"firstSeen":"2026-07-13T07:54:54.039Z","peakCount":527265,"prevCount":527265,"velocity":-100,"status":"gone"},{"url":"/weibo?q=%23%E5%86%89%E8%8E%B9%E9%A2%96%E8%AF%B4%E6%8A%8A%E5%8C%97%E4%BA%AC%E8%B4%B5%E9%98%B3%E7%BE%8E%E5%9B%BD%E7%9A%84%E6%88%BF%E5%AD%90%E9%83%BD%E5%8D%96%E4%BA%86%23","text":"冉莹颖说把北京贵阳美国的房子都卖了","count":520153,"firstSeen":"2026-07-12T16:29:39.620Z","peakCount":638116,"prevCount":520153,"velocity":-100,"status":"gone","textEn":"Ran Yingying said that she sold all the houses in the United States in Beijing, Guiyang"},{"url":"/weibo?q=%23%E5%91%A8%E6%B7%B1%E7%8E%B0%E5%9C%BA%E6%8A%8A%E4%BC%B4%E8%88%9E%E5%BC%80%E4%BA%86%23","text":"周深现场把伴舞开了","count":498881,"textEn":"Zhou Shen turned off the backup dancers on the spot","firstSeen":"2026-07-12T16:29:39.620Z","peakCount":558059,"prevCount":498881,"velocity":-100,"status":"gone"},{"url":"/weibo?q=%23%E4%B8%AD%E5%9B%BD%E7%B1%8D%E5%A5%B3%E5%8C%BB%E7%94%9F%E5%9C%A8%E6%9F%AC%E5%9F%94%E5%AF%A8%E8%AF%8A%E6%89%80%E5%86%85%E9%81%87%E5%AE%B3%23","text":"中国籍女医生在柬埔寨诊所内遇害","count":496214,"firstSeen":"2026-07-13T07:54:54.039Z","peakCount":496214,"prevCount":496214,"velocity":-100,"status":"gone"},{"url":"/weibo?q=%23%E6%8C%AA%E5%A8%81%E9%98%9F%E9%9B%86%E4%BD%93%E6%B7%B1%E5%A4%9C%E8%B5%B4%E5%A4%9C%E5%BA%97%E8%A7%A3%E5%8E%8B%23","text":"挪威队集体深夜赴夜店解压","count":495290,"firstSeen":"2026-07-13T07:54:54.039Z","peakCount":495290,"prevCount":495290,"velocity":-100,"status":"gone"},{"url":"/weibo?q=%2317%E5%9C%B0%E6%9A%B4%E9%9B%A8%23","text":"17地暴雨","count":488677,"firstSeen":"2026-07-13T07:54:54.039Z","peakCount":488677,"prevCount":488677,"velocity":-100,"status":"gone","textEn":"Heavy rain in 17 places"},{"url":"/weibo?q=%23%E5%AE%9C%E5%AE%BE%E5%9C%B0%E9%9C%87%23","text":"宜宾地震","count":469736,"textEn":"Yibin earthquake","firstSeen":"2026-07-12T23:26:10.760Z","peakCount":469736,"prevCount":469736,"velocity":-100,"status":"gone"},{"url":"/weibo?q=%23%E8%B5%9B%E5%8A%9B%E6%96%AF%E8%A7%A6%E5%8F%8A%E8%B7%8C%E5%81%9C%23","text":"赛力斯触及跌停","count":460958,"firstSeen":"2026-07-13T04:41:58.443Z","peakCount":460958,"prevCount":460958,"velocity":-100,"status":"gone"},{"url":"/weibo?q=%23%E9%9B%80%E9%AA%A88500%E4%BA%86%E7%81%BF%E5%A6%82%E7%B9%81%E6%98%9F%E8%BF%98%E6%B2%A18000%23","text":"雀骨8500了灿如繁星还没8000","count":459611,"firstSeen":"2026-07-13T07:54:54.039Z","peakCount":459611,"prevCount":459611,"velocity":-100,"status":"gone"},{"url":"/weibo?q=%23%E7%94%B7%E5%AD%90%E9%80%A0%E8%B0%A3%E6%9D%AD%E5%B7%9E%E6%9A%B4%E9%9B%A8%E5%A4%A7%E9%87%8F%E8%BD%A6%E8%BE%86%E6%B7%B9%E6%B2%A1%E8%A2%AB%E6%8B%98%23","text":"男子造谣杭州暴雨大量车辆淹没被拘","count":452020,"firstSeen":"2026-07-13T01:05:14.811Z","peakCount":452020,"prevCount":452020,"velocity":-100,"status":"gone"},{"url":"/weibo?q=%23%E8%A5%BF%E7%8F%AD%E7%89%99vs%E6%B3%95%E5%9B%BD%23","text":"西班牙vs法国","count":447585,"firstSeen":"2026-07-12T20:29:54.377Z","peakCount":447585,"prevCount":447585,"velocity":-100,"status":"gone","textEn":"Spain vs France"},{"url":"/weibo?q=%23%E4%B8%BA%E4%BB%80%E4%B9%88%E7%A9%BA%E8%B0%83%E5%BC%80%E5%88%B026%E5%BA%A6%E6%9C%89%E8%82%A1%E8%87%AD%E5%91%B3%23","text":"为什么空调开到26度有股臭味","count":417182,"firstSeen":"2026-07-13T07:54:54.039Z","peakCount":417182,"prevCount":417182,"velocity":-100,"status":"gone"},{"url":"/weibo?q=%23%E8%B4%BA%E5%B3%BB%E9%9C%96%E6%8B%92%E7%BB%9D%E5%88%98%E8%80%80%E6%96%87%23","text":"贺峻霖拒绝刘耀文","count":414576,"firstSeen":"2026-07-13T07:54:54.039Z","peakCount":414576,"prevCount":414576,"velocity":-100,"status":"gone"},{"url":"/weibo?q=%23%E6%B2%B3%E5%8C%97%E6%9A%B4%E9%9B%A86%E5%B0%8F%E6%97%B6%E9%81%93%E8%B7%AF%E7%A7%AF%E6%B0%B4%E8%B6%852%E7%B1%B3%23","text":"河北暴雨6小时道路积水超2米","count":394665,"firstSeen":"2026-07-13T04:41:58.443Z","peakCount":394665,"prevCount":394665,"velocity":-100,"status":"gone","textEn":"Heavy rain in Hebei left more than 2 meters of water on roads in 6 hours"},{"url":"/weibo?q=%23%E6%97%B6%E4%BB%A3%E5%B3%B0%E5%B3%BB%E4%B9%90%E5%8D%8EJYP%E9%83%BD%E7%BB%99%E8%8B%8F%E6%96%B0%E7%9A%93%E5%8F%91%E8%BF%87%E9%82%80%E8%AF%B7%23","text":"时代峰峻乐华JYP都给苏新皓发过邀请","count":392300,"firstSeen":"2026-07-13T04:41:58.443Z","peakCount":392300,"prevCount":392300,"velocity":-100,"status":"gone"},{"url":"/weibo?q=%23%E9%B9%BF%E6%99%97%E8%8C%83%E5%BF%97%E6%AF%85%E7%9B%B4%E6%92%AD%23","text":"鹿晗范志毅直播","count":381746,"firstSeen":"2026-07-12T16:29:39.620Z","peakCount":381746,"prevCount":381746,"velocity":-100,"status":"gone","textEn":"Lu Han and Fan Zhiyi live broadcast"},{"url":"/weibo?q=%23%E9%92%B1%E8%8A%B1%E5%9C%A8%E5%88%80%E6%8A%8A%E4%B8%8A%E5%B0%B1%E6%98%BE%E5%BE%97%E5%BE%88%E6%9C%89%E9%92%B1%23","text":"钱花在刀把上就显得很有钱","count":377922,"firstSeen":"2026-07-13T07:54:54.039Z","peakCount":377922,"prevCount":377922,"velocity":-100,"status":"gone","textEn":"Spending money on the knife handle makes you look rich"},{"url":"/weibo?q=%23%E9%87%91%E5%AD%90%E6%B6%B5%E5%8F%88%E5%BC%80%E5%A7%8B%E5%A4%A7%E7%82%B9%E5%90%8D%23","text":"金子涵又开始大点名","count":374327,"firstSeen":"2026-07-13T01:05:14.811Z","peakCount":417089,"prevCount":374327,"velocity":-100,"status":"gone"},{"url":"/weibo?q=%23%E8%89%BE%E7%B1%B3%E5%87%8C%E6%99%A8%E8%BF%9E%E5%8F%919%E6%9D%A1%E5%8D%9A%E6%96%87%23","text":"艾米凌晨连发9条博文","count":371069,"firstSeen":"2026-07-13T04:41:58.443Z","peakCount":371069,"prevCount":371069,"velocity":-100,"status":"gone"},{"url":"/weibo?q=%23%E5%A4%A7%E9%83%A8%E5%88%86%E4%BA%BA%E8%A7%89%E5%BE%97%E6%97%85%E6%B8%B8%E7%B4%AF%E7%9A%84%E5%8E%9F%E5%9B%A0%23","text":"大部分人觉得旅游累的原因","count":364691,"firstSeen":"2026-07-13T04:41:58.443Z","peakCount":900073,"prevCount":364691,"velocity":-100,"status":"gone"},{"url":"/weibo?q=%23%E7%BD%91%E4%BC%A0%E8%BF%AA%E4%B8%BD%E7%83%AD%E5%B7%B4%E9%87%91%E4%B9%9D%E5%8D%95%E5%B0%81%23","text":"网传迪丽热巴金九单封","count":344242,"firstSeen":"2026-07-13T07:54:54.039Z","peakCount":344242,"prevCount":344242,"velocity":-100,"status":"gone","textEn":"It is reported on the Internet that Dilireba Jin has nine single seals"},{"url":"/weibo?q=%23%E6%9C%89%E6%B2%A1%E6%9C%89%E4%BD%93%E9%9D%A2%E4%B8%80%E7%82%B9%E7%9A%84%E5%8D%88%E4%BC%91%E6%96%B9%E5%BC%8F%23","text":"有没有体面一点的午休方式","count":342592,"firstSeen":"2026-07-12T23:26:10.760Z","peakCount":342592,"prevCount":342592,"velocity":-100,"status":"gone"},{"url":"/weibo?q=%23%E6%B2%88%E9%98%B3%E5%9C%B0%E9%93%81%23","text":"沈阳地铁","count":331547,"firstSeen":"2026-07-13T07:54:54.039Z","peakCount":331547,"prevCount":331547,"velocity":-100,"status":"gone"},{"url":"/weibo?q=%23%E5%86%89%E8%8E%B9%E9%A2%96%E4%B8%89%E6%AC%A1%E5%8E%BB%E6%B0%91%E6%94%BF%E5%B1%80%E6%B2%A1%E7%A6%BB%E6%88%90%23","text":"冉莹颖三次去民政局没离成","count":329151,"firstSeen":"2026-07-13T01:05:14.811Z","peakCount":329151,"prevCount":329151,"velocity":-100,"status":"gone"},{"url":"/weibo?q=%23%E4%B8%8B%E5%B1%8A%E4%B8%96%E7%95%8C%E6%9D%AF%E5%B1%85%E7%84%B6%E6%9C%89%E5%85%AD%E4%B8%AA%E4%B8%BB%E5%8A%9E%E5%9B%BD%23","text":"下届世界杯居然有六个主办国","count":327922,"firstSeen":"2026-07-13T01:05:14.811Z","peakCount":327922,"prevCount":327922,"velocity":-100,"status":"gone"},{"url":"/weibo?q=%23%E9%B9%BF%E6%99%97%E5%8F%A3%E8%AF%AF%23","text":"鹿晗口误","count":327437,"firstSeen":"2026-07-13T01:05:14.811Z","peakCount":327437,"prevCount":327437,"velocity":-100,"status":"gone","textEn":"Lu Han's slip of the tongue"},{"url":"/weibo?q=%23%E9%98%BF%E6%A0%B9%E5%BB%B7%E5%A4%BA%E5%86%A0%E6%A6%82%E7%8E%87%E5%9E%AB%E5%BA%95%23","text":"阿根廷夺冠概率垫底","count":326637,"firstSeen":"2026-07-13T01:05:14.811Z","peakCount":326637,"prevCount":326637,"velocity":-100,"status":"gone"},{"url":"/weibo?q=%23%E9%95%BF%E9%91%AB%E7%A7%91%E6%8A%80%E8%B6%856000%E5%91%98%E5%B7%A5%E8%8E%B7%E8%82%A1%E4%BB%BD%23","text":"长鑫科技超6000员工获股份","count":326181,"firstSeen":"2026-07-13T04:41:58.443Z","peakCount":326181,"prevCount":326181,"velocity":-100,"status":"gone"},{"url":"/weibo?q=%23%E9%AB%98%E4%B8%AD%E7%94%9F%E6%8B%8D%E9%97%A8%E7%8E%A9%E9%97%B9%E4%BD%95%E4%BB%A5%E9%85%BF%E6%88%90%E5%91%BD%E6%A1%88%23","text":"高中生拍门玩闹何以酿成命案","count":326088,"firstSeen":"2026-07-12T16:29:39.620Z","peakCount":326088,"prevCount":326088,"velocity":-100,"status":"gone"},{"url":"/weibo?q=%23%E8%8C%83%E5%BF%97%E6%AF%85%E6%89%B9%E5%93%88%E5%85%B0%E5%BE%B7%E8%A1%A8%E7%8E%B0%E7%B3%9F%E7%B3%95%23","text":"范志毅批哈兰德表现糟糕","count":325141,"textEn":"Fan Zhiyi criticizes Haaland for poor performance","firstSeen":"2026-07-12T16:29:39.620Z","peakCount":949752,"prevCount":325141,"velocity":-100,"status":"gone"},{"url":"/weibo?q=%23%E7%81%BF%E5%A6%82%E7%B9%81%E6%98%9F%E7%83%AD%E5%BA%A6%E6%9C%AA%E7%A0%B48000%23","text":"灿如繁星热度未破8000","count":324647,"textEn":"Bright as Stars, the popularity has not exceeded 8000","firstSeen":"2026-07-12T16:29:39.620Z","peakCount":1148253,"prevCount":324647,"velocity":-100,"status":"gone"},{"url":"/weibo?q=%23%E5%B7%B4%E5%A8%81%E5%8F%91%E5%A8%81%E9%9D%92%E5%B2%9B%E5%B7%A8%E6%B5%AA%E6%BB%94%E5%A4%A9%23","text":"巴威发威青岛巨浪滔天","count":324437,"textEn":"Bawei showed off his power and huge waves surged into the sky in Qingdao","firstSeen":"2026-07-12T16:29:39.620Z","peakCount":386890,"prevCount":324437,"velocity":-100,"status":"gone"},{"url":"/weibo?q=%23%E5%B0%8F%E7%B1%B3SU7%E6%88%9020%E4%B8%87%E4%BB%A5%E4%B8%8A%E8%BD%BF%E8%BD%A66%E6%9C%88%E9%94%80%E9%87%8F%E7%AC%AC%E4%B8%80%23","text":"小米SU7成20万以上轿车6月销量第一","count":323597,"firstSeen":"2026-07-13T04:41:58.443Z","peakCount":323597,"prevCount":323597,"velocity":-100,"status":"gone"},{"url":"/weibo?q=%23%E5%91%A8%E7%BF%8A%E7%84%B6%E4%B8%8E%E5%91%A8%E5%91%A8%E5%B0%8F%E5%8F%AF%E7%88%B1%E5%90%8C%E6%A1%86%23","text":"周翊然与周周小可爱同框","count":322828,"firstSeen":"2026-07-13T04:41:58.443Z","peakCount":322828,"prevCount":322828,"velocity":-100,"status":"gone"},{"url":"/weibo?q=%23%E5%88%98%E5%AE%87%E5%AE%81%E4%BC%A4%E5%AE%B3%E6%80%A7%E4%B8%8D%E5%A4%A7%E4%BE%AE%E8%BE%B1%E6%80%A7%E6%9E%81%E5%BC%BA%23","text":"刘宇宁伤害性不大侮辱性极强","count":318523,"firstSeen":"2026-07-13T04:41:58.443Z","peakCount":318523,"prevCount":318523,"velocity":-100,"status":"gone","textEn":"Liu Yuning is not very harmful but very insulting."},{"url":"/weibo?q=%23%E5%8D%9A%E4%B8%BB%E6%8B%8D%E6%AE%B5%E5%AD%90%E5%8A%A0%E5%85%A5%E5%81%B7%E7%AA%A5%E5%A5%B3%E4%BD%8F%E6%88%B7%E5%89%A7%E6%83%85%23","text":"博主拍段子加入偷窥女住户剧情","count":316175,"firstSeen":"2026-07-13T04:41:58.443Z","peakCount":316175,"prevCount":316175,"velocity":-100,"status":"gone"},{"url":"/weibo?q=%23%E9%B9%BF%E6%99%97%E9%A3%8E%E6%B3%A2%E5%90%8E%E7%9B%B4%E6%92%AD%E9%A6%96%E9%9C%B2%E9%9D%A2%23","text":"鹿晗风波后直播首露面","count":313627,"firstSeen":"2026-07-13T04:41:58.443Z","peakCount":313627,"prevCount":313627,"velocity":-100,"status":"gone"}]