[{"url":"/weibo?q=%23%E8%A2%AB%E8%80%81%E9%BC%A0%E5%92%AC10%E5%A4%A9%E5%90%8E%E7%A1%AE%E8%AF%8A%E9%BC%A0%E5%92%AC%E7%83%AD%23","text":"被老鼠咬10天后确诊鼠咬热","count":852441,"firstSeen":"2026-04-13T01:11:26.422Z","peakCount":852441,"prevCount":0,"velocity":100,"status":"new","textEn":"Diagnosed with rat bite fever 10 days after being bitten by a rat"},{"url":"/weibo?q=%23%E4%BC%8A%E6%9C%97%E6%9B%9D%E7%BE%8E%E6%96%B9%E8%A6%81%E5%9D%87%E5%88%86%E9%9C%8D%E5%B0%94%E6%9C%A8%E5%85%B9%E6%94%B6%E7%9B%8A%23","text":"伊朗曝美方要均分霍尔木兹收益","count":657960,"firstSeen":"2026-04-13T01:11:26.422Z","peakCount":657960,"prevCount":0,"velocity":100,"status":"new"},{"url":"/weibo?q=%23%E4%BA%AC%E6%B4%9B%E5%86%8D%E6%97%A0%E4%BD%B3%E4%BA%BA%20%E5%90%B4%E7%A3%8A%23","text":"京洛再无佳人 吴磊","count":406996,"firstSeen":"2026-04-13T01:11:26.422Z","peakCount":406996,"prevCount":0,"velocity":100,"status":"new"},{"url":"/weibo?q=%23%E8%80%81%E7%99%BE%E5%A7%93%E7%9C%8B%E7%97%85%E5%BA%94%E8%AF%A5%E5%A4%9A%E7%95%99%E4%B8%AA%E5%BF%83%E7%9C%BC%23","text":"老百姓看病应该多留个心眼","count":404603,"firstSeen":"2026-04-13T01:11:26.422Z","peakCount":404603,"prevCount":0,"velocity":100,"status":"new"},{"url":"/weibo?q=%23%E8%B5%B5%E4%B8%BD%E9%A2%96%E6%9E%97%E6%9B%B4%E6%96%B0%E6%A5%9A%E4%B9%94%E4%BC%A0%E7%99%BE%E6%8C%87%23","text":"赵丽颖林更新楚乔传百指","count":315988,"firstSeen":"2026-04-13T01:11:26.422Z","peakCount":315988,"prevCount":0,"velocity":100,"status":"new"},{"url":"/weibo?q=%23%E6%A2%A6%E9%BE%99%E5%B9%BF%E5%91%8A%20%E8%8A%AD%E8%95%BE%E8%88%9E%E9%9E%8B%23","text":"梦龙广告 芭蕾舞鞋","count":233940,"firstSeen":"2026-04-13T01:11:26.422Z","peakCount":233940,"prevCount":0,"velocity":100,"status":"new"},{"url":"/weibo?q=%23%E5%9B%BD%E9%99%85%E6%B2%B9%E4%BB%B7%E5%A4%A7%E5%B9%85%E4%B8%8A%E6%B6%A8%23","text":"国际油价大幅上涨","count":158766,"firstSeen":"2026-04-13T01:11:26.422Z","peakCount":158766,"prevCount":0,"velocity":100,"status":"new"},{"url":"/weibo?q=%23%E5%BE%90%E8%89%BA%E6%B4%8B%E7%AB%9F%E7%84%B6%E5%92%8C%E5%AD%99%E6%80%A1%E5%90%88%E4%BD%9C%E8%BF%87%23","text":"徐艺洋竟然和孙怡合作过","count":155339,"firstSeen":"2026-04-13T01:11:26.422Z","peakCount":155339,"prevCount":0,"velocity":100,"status":"new"},{"url":"/weibo?q=%23%E6%BC%94%E5%91%98%E9%83%91%E9%9B%B7%E5%8E%BB%E4%B8%96%23","text":"演员郑雷去世","count":145585,"firstSeen":"2026-04-13T01:11:26.422Z","peakCount":145585,"prevCount":0,"velocity":100,"status":"new"},{"url":"/weibo?q=%23%E5%BC%A0%E9%9B%AA%E9%97%AE%E4%BA%86%E8%87%AA%E5%B7%B13%E4%B8%AA%E9%97%AE%E9%A2%98%E5%90%8E%E8%BE%9E%E8%81%8C%23","text":"张雪问了自己3个问题后辞职","count":129222,"firstSeen":"2026-04-13T01:11:26.422Z","peakCount":129222,"prevCount":0,"velocity":100,"status":"new"},{"url":"/weibo?q=%23%E5%8C%97%E4%BA%AC%E9%87%8E%E7%94%9F%E5%8A%A8%E7%89%A9%E5%9B%AD%E8%B1%9A%E8%B1%9A%E6%83%85%E7%BB%AA%E7%A8%B3%E5%AE%9A%E6%B6%88%E7%81%AD%E6%9D%A8%E7%B5%AE%23","text":"北京野生动物园豚豚情绪稳定消灭杨絮","count":127761,"firstSeen":"2026-04-13T01:11:26.422Z","peakCount":127761,"prevCount":0,"velocity":100,"status":"new","textEn":"Dolphins in Beijing Wildlife Park are emotionally stable and eliminate Yang Xu"},{"url":"/weibo?q=%23%E5%A5%B3%E5%AD%90%E8%BF%9E%E5%90%83%E4%B8%A4%E5%A4%A9%E8%93%9D%E8%8E%93%E8%83%83%E9%87%8C%E5%A0%B5%E6%88%90%E7%9F%B3%E5%A2%99%23","text":"女子连吃两天蓝莓胃里堵成石墙","count":103789,"firstSeen":"2026-04-13T01:11:26.422Z","peakCount":103789,"prevCount":0,"velocity":100,"status":"new"},{"url":"/weibo?q=%23%E4%B8%A4%E8%BD%A6%E5%89%90%E8%B9%AD%E8%97%8F%E6%97%8F%E5%A4%A7%E5%93%A5%E5%9D%9A%E6%8C%81%E8%B5%94%E5%81%BF%E5%A5%B3%E5%AD%90%E5%A9%89%E6%8B%92%23","text":"两车剐蹭藏族大哥坚持赔偿女子婉拒","count":100409,"firstSeen":"2026-04-13T01:11:26.422Z","peakCount":100409,"prevCount":0,"velocity":100,"status":"new"},{"url":"/weibo?q=%23%E4%BC%8A%E6%9C%97%E6%80%BB%E7%BB%9F%E7%A7%B0%E7%BE%8E%E4%BC%8A%E8%B0%88%E5%88%A4%E5%B7%B2%E6%AF%AB%E6%97%A0%E6%84%8F%E4%B9%89%23","text":"伊朗总统称美伊谈判已毫无意义","count":99282,"firstSeen":"2026-04-13T01:11:26.422Z","peakCount":99282,"prevCount":0,"velocity":100,"status":"new"},{"url":"/weibo?q=%23%E5%AE%98%E6%96%B9%E9%80%9A%E6%8A%A5%E4%BB%8E%E4%BA%91%E5%8D%97%E6%8B%8911%E5%90%A8%E8%A5%BF%E7%93%9C%E5%85%A8%E5%9D%8F%23","text":"官方通报从云南拉11吨西瓜全坏","count":98551,"firstSeen":"2026-04-13T01:11:26.422Z","peakCount":98551,"prevCount":0,"velocity":100,"status":"new"},{"url":"/weibo?q=%23%E5%A5%B3%E5%AD%90%E6%88%B4%E7%BE%8E%E7%9E%B3%E5%8D%81%E5%87%A0%E5%B9%B4%E7%9C%BC%E8%A7%92%E8%86%9C%E9%95%BF%E7%96%99%E7%98%A9%23","text":"女子戴美瞳十几年眼角膜长疙瘩","count":98404,"firstSeen":"2026-04-13T01:11:26.422Z","peakCount":98404,"prevCount":0,"velocity":100,"status":"new"},{"url":"/weibo?q=%23%E6%AF%8F%E5%A4%A9%E5%81%9A%E5%A5%BD%E8%BF%993%E4%BB%B6%E4%BA%8B%E8%83%BD%E5%BB%B6%E5%AF%BF%E8%BF%9110%E5%B9%B4%23","text":"每天做好这3件事能延寿近10年","count":95888,"firstSeen":"2026-04-13T01:11:26.422Z","peakCount":95888,"prevCount":0,"velocity":100,"status":"new"},{"url":"/weibo?q=%23%E9%AB%98%E9%93%81%E7%AB%99%E5%B7%A5%E4%BD%9C%E4%BA%BA%E5%91%98%E5%9B%9E%E5%BA%94%E7%AB%99%E5%8F%B0%E5%85%A8%E9%9D%A2%E7%A6%81%E7%83%9F%23","text":"高铁站工作人员回应站台全面禁烟","count":94971,"firstSeen":"2026-04-13T01:11:26.422Z","peakCount":94971,"prevCount":0,"velocity":100,"status":"new"},{"url":"/weibo?q=%23%E5%AE%8B%E4%BA%9A%E8%BD%A9%20%E6%B2%A1%E5%89%AF%E6%AD%8C%23","text":"宋亚轩 没副歌","count":91531,"firstSeen":"2026-04-13T01:11:26.422Z","peakCount":91531,"prevCount":0,"velocity":100,"status":"new"},{"url":"/weibo?q=%23%E5%B0%8F%E7%8C%AB%E5%B1%85%E7%84%B6%E7%90%86%E8%A7%A3%E4%BA%86%E5%BD%B1%E5%AD%90%23","text":"小猫居然理解了影子","count":82540,"firstSeen":"2026-04-13T01:11:26.422Z","peakCount":82540,"prevCount":0,"velocity":100,"status":"new"},{"url":"/weibo?q=%23%E4%BC%8A%E6%9C%97%E7%A7%B0%E7%BE%8E%E5%9B%BD%E8%8D%92%E5%94%90%E5%8F%AF%E7%AC%91%23","text":"伊朗称美国荒唐可笑","count":75681,"firstSeen":"2026-04-13T01:11:26.422Z","peakCount":75681,"prevCount":0,"velocity":100,"status":"new","textEn":"Iran calls the United States ridiculous"},{"url":"/weibo?q=%23%E8%B0%A2%E9%9C%86%E9%94%8B%E7%9A%84%E7%A0%B4%E6%B4%9E%E7%89%9B%E4%BB%94%E8%A3%A4%E8%83%BD%E7%9C%8B%E5%88%B0%E5%BA%95%E8%A3%A4%23","text":"谢霆锋的破洞牛仔裤能看到底裤","count":73638,"firstSeen":"2026-04-13T01:11:26.422Z","peakCount":73638,"prevCount":0,"velocity":100,"status":"new"},{"url":"/weibo?q=%23%E7%88%B5%E5%A3%ABvs%E6%B9%96%E4%BA%BA%23","text":"爵士vs湖人","count":70191,"firstSeen":"2026-04-13T01:11:26.422Z","peakCount":70191,"prevCount":0,"velocity":100,"status":"new"},{"url":"/weibo?q=%23%E8%B5%B5%E5%AD%90%E7%90%AA%E6%9B%BE%E7%A1%AC%E5%88%9A%E6%90%9C%E7%8B%90%23","text":"赵子琪曾硬刚搜狐","count":65215,"firstSeen":"2026-04-13T01:11:26.422Z","peakCount":65215,"prevCount":0,"velocity":100,"status":"new"},{"url":"/weibo?q=%23%E6%8E%98%E9%87%91vs%E9%A9%AC%E5%88%BA%23","text":"掘金vs马刺","count":61823,"firstSeen":"2026-04-13T01:11:26.422Z","peakCount":61823,"prevCount":0,"velocity":100,"status":"new"},{"url":"/weibo?q=%23%E5%93%A9%E5%B8%83%E5%93%A9%E5%B8%83AI%E8%A2%AB%E6%9B%9D%E7%94%9F%E6%88%90%E6%B6%89%E9%BB%84%E8%BF%9D%E8%A7%84%E8%A7%86%E9%A2%91%23","text":"哩布哩布AI被曝生成涉黄违规视频","count":61327,"firstSeen":"2026-04-13T01:11:26.422Z","peakCount":61327,"prevCount":0,"velocity":100,"status":"new"},{"url":"/weibo?q=%23%E5%91%98%E5%B7%A5%E4%B8%AD%E4%BA%861500%E4%B8%87%E5%BD%A9%E7%A5%A8%E5%90%8E%E7%9B%B4%E6%8E%A5%E7%A6%BB%E8%81%8C%23","text":"员工中了1500万彩票后直接离职","count":1285539,"textEn":"Employee resigned immediately after winning 15 million yuan in lottery","firstSeen":"2026-04-12T16:05:16.357Z","peakCount":1497208,"prevCount":1032638,"velocity":24,"status":"rising"},{"url":"/weibo?q=%23OPPOFindX9Ultra%E4%BB%8A%E6%97%A5%E5%AE%98%E5%AE%A3%23","text":"OPPOFindX9Ultra今日官宣","count":666916,"textEn":"OPPO Find X9 Ultra is officially announced today","firstSeen":"2026-04-12T21:04:55.687Z","peakCount":666916,"prevCount":514112,"velocity":30,"status":"rising"},{"url":"/weibo?q=%23%E4%B8%AD%E5%9B%BD%E8%88%AA%E5%A4%A9%E4%B8%8D%E6%96%AD%E5%88%B7%E6%96%B0%E5%AE%87%E5%AE%99%E7%BA%A7%E7%B2%BE%E5%BD%A9%23","text":"中国航天不断刷新宇宙级精彩","count":677429,"textEn":"China's aerospace industry continues to create world-class excitement","firstSeen":"2026-04-12T16:05:16.357Z","peakCount":716799,"prevCount":609992,"velocity":11,"status":"hot"},{"url":"/weibo?q=%23%E5%A5%B3%E5%AD%90%E9%81%AD%E6%B3%95%E5%AE%98%E7%8C%A5%E4%BA%B516%E5%88%86%E9%92%9F%E5%BD%95%E9%9F%B3%E6%9B%9D%E5%85%89%23","text":"女子遭法官猥亵16分钟录音曝光","count":152408,"firstSeen":"2026-04-12T16:05:16.357Z","peakCount":396663,"prevCount":165720,"velocity":-8,"status":"hot"},{"url":"/weibo?q=%23%E7%9F%AD%E5%89%A7%E5%89%A7%E5%AE%A3%E8%AF%AF%E5%85%A5%E8%B1%AA%E9%97%A8%E5%B0%91%E5%A4%AB%E4%BA%BA%E8%81%9A%E4%BC%9A%E5%B1%80%23","text":"短剧剧宣误入豪门少夫人聚会局","count":117301,"textEn":"The short play tells the story of accidentally entering a party of a wealthy young lady.","firstSeen":"2026-04-12T23:46:29.987Z","peakCount":117301,"prevCount":106444,"velocity":10,"status":"hot"},{"url":"/weibo?q=%23%E9%83%91%E6%81%BA%E6%99%92%E5%A5%B3%E5%84%BF%E5%85%A8%E8%8B%B1%E6%96%87%E5%AF%B9%E8%AF%9D%23","text":"郑恺晒女儿全英文对话","count":104285,"firstSeen":"2026-04-12T23:46:29.987Z","peakCount":114552,"prevCount":114552,"velocity":-9,"status":"hot"},{"url":"/weibo?q=%23%E7%94%B7%E5%AD%90%E6%8E%8914%E9%A2%97%E7%89%99%E5%89%A9%E4%B8%8B14%E9%A2%97%E4%B9%9F%E5%BE%97%E5%85%A8%E6%8B%94%E6%8E%89%23","text":"男子掉14颗牙剩下14颗也得全拔掉","count":102396,"firstSeen":"2026-04-12T23:46:29.987Z","peakCount":114949,"prevCount":114949,"velocity":-11,"status":"hot"},{"url":"/weibo?q=%23%E7%AE%B1%E5%8C%85%E5%A5%B3%E7%8E%8B%E7%A0%B4%E4%BA%A7%E5%90%8E%E5%8D%96%E5%8C%85%E5%AD%90%E9%87%8D%E5%90%AF%E4%BA%BA%E7%94%9F%23","text":"箱包女王破产后卖包子重启人生","count":100677,"firstSeen":"2026-04-12T23:46:29.987Z","peakCount":103494,"prevCount":103494,"velocity":-3,"status":"hot"},{"url":"/weibo?q=%2312306%E5%9B%9E%E5%BA%94%E9%9D%99%E9%9F%B3%E8%BD%A6%E5%8E%A2%E5%94%AE%E8%B4%A7%E4%B8%8D%E5%8F%AB%E5%8D%96%23","text":"12306回应静音车厢售货不叫卖","count":99735,"textEn":"12306 responded to sales in silent carriages instead of hawking","firstSeen":"2026-04-12T23:46:29.987Z","peakCount":99735,"prevCount":95952,"velocity":4,"status":"hot"},{"url":"/weibo?q=%23%E5%AD%99%E5%AD%90%E6%80%95%E7%88%B7%E7%88%B7%E5%8E%BB%E4%B8%96%E6%AF%8F%E5%A4%A9%E5%81%B7%E5%81%B7%E5%B8%A6%E8%82%89%E5%9B%9E%E5%AE%B6%23","text":"孙子怕爷爷去世每天偷偷带肉回家","count":96106,"textEn":"My grandson is afraid that his grandfather will die and he secretly brings meat home every day.","firstSeen":"2026-04-12T16:05:16.357Z","peakCount":121683,"prevCount":107171,"velocity":-10,"status":"hot"},{"url":"/weibo?q=%23%E7%8E%8B%E7%9F%B3%E5%90%A6%E8%AE%A4%E8%A2%AB%E6%8A%93%23","text":"王石否认被抓","count":76979,"textEn":"Wang Shi denies being arrested","firstSeen":"2026-04-12T16:05:16.357Z","peakCount":122157,"prevCount":64418,"velocity":19,"status":"hot"},{"url":"/weibo?q=%23%E6%AC%A7%E5%B0%94%E7%8F%AD%E6%89%BF%E8%AE%A4%E8%B4%A5%E9%80%89%23","text":"欧尔班承认败选","count":290709,"textEn":"Orban admits defeat","firstSeen":"2026-04-12T23:46:29.987Z","peakCount":432436,"prevCount":432436,"velocity":-33,"status":"falling"},{"url":"/weibo?q=%23%E7%BD%91%E4%BC%A0%E6%B5%AA%E5%A7%907%E4%B8%80%E5%85%AC%E4%B8%AA%E4%BA%BA%E5%96%9C%E7%88%B1%E5%BA%A6%E6%8E%92%E5%90%8D%23","text":"网传浪姐7一公个人喜爱度排名","count":139728,"textEn":"According to the Internet, the personal favorite ranking of Sister Lang 7","firstSeen":"2026-04-12T16:05:16.357Z","peakCount":848015,"prevCount":743083,"velocity":-81,"status":"falling"},{"url":"/weibo?q=%23%E6%9C%B4%E5%AE%9D%E5%89%91%E6%8E%A2%E7%8F%AD%E7%8E%8B%E5%AE%89%E5%AE%87%23","text":"朴宝剑探班王安宇","count":114369,"textEn":"Park Bo Gum visits Wang Anyu","firstSeen":"2026-04-12T16:05:16.357Z","peakCount":154355,"prevCount":154355,"velocity":-26,"status":"falling"},{"url":"/weibo?q=%23%E4%BC%8A%E6%9C%97%E5%85%AC%E5%B8%83%E9%A9%B1%E7%A6%BB%E7%BE%8E%E5%86%9B%E8%88%B0%E8%A7%86%E9%A2%91%23","text":"伊朗公布驱离美军舰视频","count":107608,"firstSeen":"2026-04-12T23:46:29.987Z","peakCount":252976,"prevCount":252976,"velocity":-57,"status":"falling"},{"url":"/weibo?q=%23%E4%BB%99%E9%80%86%E7%8E%8B%E6%9E%97%23","text":"仙逆王林","count":104662,"firstSeen":"2026-04-12T23:46:29.987Z","peakCount":177856,"prevCount":177856,"velocity":-41,"status":"falling"},{"url":"/weibo?q=%23%E5%8C%88%E7%89%99%E5%88%A9%23","text":"匈牙利","count":103028,"firstSeen":"2026-04-12T23:46:29.987Z","peakCount":157523,"prevCount":157523,"velocity":-35,"status":"falling"},{"url":"/weibo?q=%23%E5%AE%98%E6%96%B9%E5%9B%9E%E5%BA%94%E4%B8%BA%E4%BB%80%E4%B9%88%E4%B8%8D%E8%83%BD%E6%8A%8A%E6%9D%A8%E6%9F%B3%E6%A0%91%E9%83%BD%E7%A0%8D%E4%BA%86%23","text":"官方回应为什么不能把杨柳树都砍了","count":101762,"textEn":"Official response: Why can’t all willow trees be cut down?","firstSeen":"2026-04-12T16:05:16.357Z","peakCount":201617,"prevCount":191955,"velocity":-47,"status":"falling"},{"url":"/weibo?q=%23%E8%B5%B5%E5%AD%90%E7%90%AA%E7%A1%AC%E5%88%9A%E6%B5%AA%E5%A7%90%23","text":"赵子琪硬刚浪姐","count":101253,"firstSeen":"2026-04-12T16:05:16.357Z","peakCount":145346,"prevCount":129832,"velocity":-22,"status":"falling"},{"url":"/weibo?q=%23%E5%A2%83%E5%A4%96%E6%B6%89%E9%BB%84AI%E8%BD%AF%E4%BB%B6%E7%BB%95%E8%BF%87%E7%9B%91%E7%AE%A1%E6%B5%81%E5%85%A5%E5%9B%BD%E5%86%85%23","text":"境外涉黄AI软件绕过监管流入国内","count":93276,"firstSeen":"2026-04-12T16:05:16.357Z","peakCount":186110,"prevCount":186110,"velocity":-50,"status":"falling"},{"url":"/weibo?q=%23A%E8%82%A1%E4%BA%A4%E6%98%93%E5%B0%86%E8%BF%8E%E9%87%8D%E8%A6%81%E8%B0%83%E6%95%B4%23","text":"A股交易将迎重要调整","count":82189,"firstSeen":"2026-04-12T23:46:29.987Z","peakCount":149046,"prevCount":149046,"velocity":-45,"status":"falling"},{"url":"/weibo?q=%23%E5%BC%A0%E9%9B%AA%E6%9C%BA%E8%BD%A6%E7%AB%9E%E6%8B%8D%E8%80%85%E6%8B%92%E7%BB%9D%E5%8A%A0%E4%BB%B7500%E4%B8%87%E8%BD%AC%E5%94%AE%23","text":"张雪机车竞拍者拒绝加价500万转售","count":80495,"textEn":"Zhang Xue's motorcycle bidder refused to increase the price by 5 million for resale","firstSeen":"2026-04-12T16:05:16.357Z","peakCount":150415,"prevCount":150415,"velocity":-46,"status":"falling"},{"url":"/weibo?q=%23%E7%94%B7%E5%AD%90%E4%BD%8F48%E5%85%83%E5%AE%BE%E9%A6%86%E8%BA%AB%E4%BA%A1%E5%AE%B6%E5%B1%9E%E7%B4%A2%E8%B5%94%E8%A2%AB%E9%A9%B3%E5%9B%9E%23","text":"男子住48元宾馆身亡家属索赔被驳回","count":68478,"textEn":"Man’s family’s claim for death after staying in a 48-yuan hotel was rejected","firstSeen":"2026-04-12T16:56:05.188Z","peakCount":123488,"prevCount":123488,"velocity":-45,"status":"falling"},{"url":"/weibo?q=%23%E6%9D%8E%E8%8D%A3%E6%B5%A9%E7%9C%9F%E8%BD%AC%E6%88%91%E4%BA%94%E7%99%BE%E4%BA%86%23","text":"李荣浩真转我五百了","count":64695,"firstSeen":"2026-04-12T16:05:16.357Z","peakCount":148862,"prevCount":107029,"velocity":-40,"status":"falling"},{"url":"/weibo?q=%23%E7%8E%8B%E6%A9%B9%E6%9D%B0%E5%B0%8F%E5%92%B4%E6%95%85%E4%BA%8B%E5%8E%9F%E5%9E%8B%23","text":"王橹杰小咴故事原型","count":61752,"firstSeen":"2026-04-12T23:46:29.987Z","peakCount":97028,"prevCount":97028,"velocity":-36,"status":"falling"},{"url":"/weibo?q=%23%E5%B7%A7%E4%B9%90%E5%85%B9%E5%93%88%E5%88%A9%E6%B3%A2%E7%89%B9%E6%89%93%E5%BC%80%E5%BF%AB%E4%B9%90%E9%AD%94%E6%B3%95%E5%85%A5%E5%8F%A3%23","text":"巧乐兹哈利波特打开快乐魔法入口","count":218864,"textEn":"Qolaoz Harry Potter opens the entrance to happy magic","firstSeen":"2026-04-12T17:38:37.862Z","peakCount":218864,"prevCount":218864,"velocity":-100,"status":"gone"},{"url":"/weibo?q=%23%E6%A5%9A%E4%B9%94%E4%BC%A0%E7%83%AD%E5%BA%A6%23","text":"楚乔传热度","count":181095,"textEn":"Chu Qiao heat transfer rate","firstSeen":"2026-04-12T18:23:51.235Z","peakCount":181095,"prevCount":181095,"velocity":-100,"status":"gone"},{"url":"/weibo?q=%23%E5%88%87%E5%B0%94%E8%A5%BF0%E6%AF%943%E6%9B%BC%E5%9F%8E%23","text":"切尔西0比3曼城","count":172741,"firstSeen":"2026-04-12T23:46:29.987Z","peakCount":172741,"prevCount":172741,"velocity":-100,"status":"gone"},{"url":"/weibo?q=%23%E9%AB%98%E4%B8%89%E5%AD%A6%E7%94%9F%E5%AD%A6%E4%B9%A0%E5%9B%B0%E9%9A%BE%E6%B5%8B%E5%87%BA%E6%99%BA%E9%9A%9C%23","text":"高三学生学习困难测出智障","count":134770,"firstSeen":"2026-04-12T23:46:29.987Z","peakCount":134770,"prevCount":134770,"velocity":-100,"status":"gone","textEn":"High school senior student with learning difficulties found to be mentally retarded"},{"url":"/weibo?q=%23%E4%BC%8A%E6%9C%97%E4%BC%8A%E6%96%AF%E5%85%B0%E9%9D%A9%E5%91%BD%E5%8D%AB%E9%98%9F%E6%B5%B7%E5%86%9B%E5%8F%91%E5%87%BA%E8%AD%A6%E5%91%8A%23","text":"伊朗伊斯兰革命卫队海军发出警告","count":133266,"textEn":"Iran's Islamic Revolutionary Guard Corps Navy issues warning","firstSeen":"2026-04-12T16:05:16.357Z","peakCount":143150,"prevCount":133266,"velocity":-100,"status":"gone"},{"url":"/weibo?q=%23%E4%BC%8A%E6%9C%97%E7%A7%B0%E7%BE%8E%E5%9B%BD%E6%89%BE%E5%80%9F%E5%8F%A3%E9%80%80%E5%87%BA%E8%B0%88%E5%88%A4%23","text":"伊朗称美国找借口退出谈判","count":114967,"textEn":"Iran says U.S. is looking for excuses to withdraw from talks","firstSeen":"2026-04-12T17:38:37.862Z","peakCount":195630,"prevCount":114967,"velocity":-100,"status":"gone"},{"url":"/weibo?q=%23%E7%8E%8B%E7%9F%B3%E5%B7%B2%E7%AC%AC4%E6%AC%A1%E8%A2%AB%E4%BC%A0%E5%A4%B1%E8%81%94%E8%A2%AB%E6%8A%93%23","text":"王石已第4次被传失联被抓","count":112689,"textEn":"Wang Shi was reported to have lost contact and was arrested for the fourth time","firstSeen":"2026-04-12T19:53:58.215Z","peakCount":112689,"prevCount":112689,"velocity":-100,"status":"gone"},{"url":"/weibo?q=%23%E6%99%BA%E7%BE%8E%E5%A4%A7%E4%BA%94%E5%BA%A7%E9%A3%8E%E4%BA%91T9L%E5%85%A8%E7%90%83%E4%B8%8A%E5%B8%82%23","text":"智美大五座风云T9L全球上市","count":112489,"firstSeen":"2026-04-12T18:23:51.235Z","peakCount":112489,"prevCount":112489,"velocity":-100,"status":"gone"},{"url":"/weibo?q=%23%E6%97%B6%E4%BB%A3%E5%B0%91%E5%B9%B4%E5%9B%A2%E4%B8%8E%E5%BE%AA%E8%A7%84%E8%B9%88%E7%9F%A9%E5%94%B1%E5%8F%8D%E8%B0%83%23","text":"时代少年团与循规蹈矩唱反调","count":109244,"firstSeen":"2026-04-12T23:46:29.987Z","peakCount":109244,"prevCount":109244,"velocity":-100,"status":"gone"},{"url":"/weibo?q=%23%E7%8E%8B%E6%BF%9B%E7%9A%84%E5%BA%95%E6%B0%94%23","text":"王濛的底气","count":109005,"textEn":"Wang Meng’s confidence","firstSeen":"2026-04-12T16:05:16.357Z","peakCount":109005,"prevCount":109005,"velocity":-100,"status":"gone"},{"url":"/weibo?q=%23%E7%8E%8B%E7%9F%B3%20%E7%A7%A6%E6%9E%AB%23","text":"王石 秦枫","count":108469,"textEn":"Wang Shi Qin Feng","firstSeen":"2026-04-12T16:05:16.357Z","peakCount":148583,"prevCount":108469,"velocity":-100,"status":"gone"},{"url":"/weibo?q=%23%E8%84%91%E9%9B%BE%23","text":"脑雾","count":107934,"textEn":"brain fog","firstSeen":"2026-04-12T16:56:05.188Z","peakCount":107934,"prevCount":107934,"velocity":-100,"status":"gone"},{"url":"/weibo?q=%23%E4%BD%95%E8%B6%85%E8%95%B8%E5%8E%BB%E4%B8%96%23","text":"何超蕸去世","count":105791,"textEn":"He Chaogui passed away","firstSeen":"2026-04-12T16:05:16.357Z","peakCount":121804,"prevCount":105791,"velocity":-100,"status":"gone"},{"url":"/weibo?q=%23%E5%A6%88%E5%A6%88%E8%BE%85%E5%AF%BC%E4%BD%9C%E4%B8%9A%E8%A2%AB%E6%B0%94%E5%88%B0%E5%BC%95%E7%88%86%E8%84%91%E7%98%A4%23","text":"妈妈辅导作业被气到引爆脑瘤","count":105084,"firstSeen":"2026-04-12T16:05:16.357Z","peakCount":110206,"prevCount":105084,"velocity":-100,"status":"gone"},{"url":"/weibo?q=%23%E5%8C%97%E4%BA%AC%E9%80%90%E6%AD%A5%E6%9B%BF%E6%8D%A2%E6%9D%A8%E6%9F%B3%E6%A0%91%E9%9B%8C%E6%A0%AA%23","text":"北京逐步替换杨柳树雌株","count":105024,"firstSeen":"2026-04-12T20:34:16.727Z","peakCount":105024,"prevCount":105024,"velocity":-100,"status":"gone"},{"url":"/weibo?q=%23%E5%8C%88%E7%89%99%E5%88%A9%E5%9B%BD%E4%BC%9A%E9%80%89%E4%B8%BE%E8%92%82%E8%90%A8%E5%85%9A%E9%A2%86%E5%85%88%23","text":"匈牙利国会选举蒂萨党领先","count":104052,"firstSeen":"2026-04-12T23:46:29.987Z","peakCount":104052,"prevCount":104052,"velocity":-100,"status":"gone"},{"url":"/weibo?q=%23%E9%92%A2%E9%93%81%E6%A3%AE%E6%9E%97%E5%A4%A7%E7%BB%93%E5%B1%80%23","text":"钢铁森林大结局","count":103328,"firstSeen":"2026-04-12T16:05:16.357Z","peakCount":177423,"prevCount":103328,"velocity":-100,"status":"gone"},{"url":"/weibo?q=%23%E5%B0%8F%E9%85%92%E7%AA%9D%E5%92%8C%E7%88%B8%E7%88%B8%E9%80%9B%E9%9D%A2%E5%8C%85%E8%8A%82%23","text":"小酒窝和爸爸逛面包节","count":102665,"textEn":"Xiao Dimple and Dad visit the Bread Festival","firstSeen":"2026-04-12T16:05:16.357Z","peakCount":145020,"prevCount":102665,"velocity":-100,"status":"gone"},{"url":"/weibo?q=%23%E7%99%BD%E6%A1%83%E6%98%9F%E5%BA%A7%E4%B8%80%E5%91%A8%E8%BF%90%E5%8A%BF%23","text":"白桃星座一周运势","count":101955,"textEn":"Weekly horoscope for Baitao zodiac sign","firstSeen":"2026-04-12T16:05:16.357Z","peakCount":210350,"prevCount":101955,"velocity":-100,"status":"gone"},{"url":"/weibo?q=%23%E5%A4%AE%E8%A7%86%E6%9B%9D%E5%85%89AI%E9%80%A0%E9%BB%84%E4%BA%A7%E4%B8%9A%E9%93%BE%23","text":"央视曝光AI造黄产业链","count":101619,"textEn":"CCTV exposes AI yellowing industry chain","firstSeen":"2026-04-12T16:05:16.357Z","peakCount":149846,"prevCount":101619,"velocity":-100,"status":"gone"},{"url":"/weibo?q=%23%E4%BC%8A%E6%9C%97%E8%B0%88%E5%88%A4%E4%BB%A3%E8%A1%A8%E5%9B%A2%E5%90%AF%E7%A8%8B%E5%9B%9E%E5%9B%BD%23","text":"伊朗谈判代表团启程回国","count":100841,"firstSeen":"2026-04-12T23:46:29.987Z","peakCount":100841,"prevCount":100841,"velocity":-100,"status":"gone"},{"url":"/weibo?q=%23%E7%BD%97%E6%B0%B8%E6%B5%A9%E6%98%AF%E6%80%8E%E4%B9%88%E8%A2%AB%E8%92%B8%E9%A6%8F%E7%9A%84%23","text":"罗永浩是怎么被蒸馏的","count":100762,"textEn":"How was Luo Yonghao distilled?","firstSeen":"2026-04-12T16:05:16.357Z","peakCount":100762,"prevCount":100762,"velocity":-100,"status":"gone"},{"url":"/weibo?q=%23%E7%83%AD%E5%88%BA%20%E9%99%8D%E7%BA%A7%23","text":"热刺 降级","count":100021,"textEn":"Tottenham relegated","firstSeen":"2026-04-12T16:05:16.357Z","peakCount":100021,"prevCount":100021,"velocity":-100,"status":"gone"},{"url":"/weibo?q=%23%E9%83%91%E4%B8%BD%E6%96%87%E8%AF%95%E4%B9%98%E5%B0%8F%E7%B1%B3%E6%B1%BD%E8%BD%A6%23","text":"郑丽文试乘小米汽车","count":99463,"textEn":"Zheng Liwen takes a test drive in a Xiaomi car","firstSeen":"2026-04-12T16:05:16.357Z","peakCount":99463,"prevCount":99463,"velocity":-100,"status":"gone"},{"url":"/weibo?q=%23%E4%BA%95%E6%9F%8F%E7%84%B6%E8%83%A1%E5%B7%B4%E5%A6%88%23","text":"井柏然胡巴妈","count":99056,"textEn":"Jing Boran Huba's mother","firstSeen":"2026-04-12T16:56:05.188Z","peakCount":118307,"prevCount":99056,"velocity":-100,"status":"gone"},{"url":"/weibo?q=%23%E8%8B%B9%E6%9E%9CAI%E7%9C%BC%E9%95%9C%E7%BB%86%E8%8A%82%E6%9B%9D%E5%85%89%23","text":"苹果AI眼镜细节曝光","count":98691,"firstSeen":"2026-04-12T23:46:29.987Z","peakCount":98691,"prevCount":98691,"velocity":-100,"status":"gone"},{"url":"/weibo?q=%23%E7%BE%8E%E5%86%9B%E7%A7%B0%E5%B0%86%E5%B0%81%E9%94%81%E4%BC%8A%E6%B8%AF%E5%8F%A3%E6%B5%B7%E4%B8%8A%E4%BA%A4%E9%80%9A%23","text":"美军称将封锁伊港口海上交通","count":97849,"firstSeen":"2026-04-12T23:46:29.987Z","peakCount":97849,"prevCount":97849,"velocity":-100,"status":"gone"},{"url":"/weibo?q=%23%E5%85%A8%E7%90%83%E8%88%AA%E5%8F%B8%E8%A2%AB%E8%BF%AB%E6%B6%A8%E4%BB%B7%23","text":"全球航司被迫涨价","count":97447,"textEn":"Global airlines forced to raise prices","firstSeen":"2026-04-12T18:23:51.235Z","peakCount":97447,"prevCount":97447,"velocity":-100,"status":"gone"},{"url":"/weibo?q=%23%E5%AD%99%E7%87%95%E5%A7%BF%E6%BC%94%E5%94%B1%E4%BC%9A%23","text":"孙燕姿演唱会","count":96128,"firstSeen":"2026-04-12T16:05:16.357Z","peakCount":123381,"prevCount":96128,"velocity":-100,"status":"gone","textEn":"Stefanie Sun concert"},{"url":"/weibo?q=%23%E5%88%98%E8%AF%97%E9%9B%AF%E8%B0%A2%E8%B0%A2%E5%A4%A7%E5%AE%B6%E7%9A%84%E7%88%B1%E5%92%8C%E7%A5%9D%E7%A6%8F%23","text":"刘诗雯谢谢大家的爱和祝福","count":69592,"firstSeen":"2026-04-12T16:05:16.357Z","peakCount":69592,"prevCount":69592,"velocity":-100,"status":"gone","textEn":"Liu Shiwen thanks everyone for your love and blessings"},{"url":"/weibo?q=%23%E4%BC%8A%E6%9C%97%E7%A7%B0%E6%8B%A6%E6%88%AA%E7%BE%8E%E8%88%B0%E8%BF%9B%E5%85%A5%E9%9C%8D%E5%B0%94%E6%9C%A8%E5%85%B9%E6%B5%B7%E5%B3%A1%23","text":"伊朗称拦截美舰进入霍尔木兹海峡","count":67069,"textEn":"Iran says it intercepts US ship entering Strait of Hormuz","firstSeen":"2026-04-12T16:05:16.357Z","peakCount":67069,"prevCount":67069,"velocity":-100,"status":"gone"},{"url":"/weibo?q=%23IU%E6%96%B0%E5%89%A7%E5%90%91%E7%94%B7%E4%B8%BB%E6%B1%82%E5%A9%9A%E8%BF%99%E6%AE%B5%23","text":"IU新剧向男主求婚这段","count":66182,"textEn":"IU proposes to male lead in new drama","firstSeen":"2026-04-12T17:38:37.862Z","peakCount":66182,"prevCount":66182,"velocity":-100,"status":"gone"},{"url":"/weibo?q=%23%E6%B3%95%E5%AE%98%E8%A2%AB%E6%9B%9D%E5%9C%A8%E5%8A%9E%E5%85%AC%E5%AE%A4%E7%8C%A5%E4%BA%B5%E7%A6%BB%E5%A9%9A%E6%A1%88%E5%BD%93%E4%BA%8B%E4%BA%BA%23","text":"法官被曝在办公室猥亵离婚案当事人","count":65935,"textEn":"A judge was exposed for molesting a client in a divorce case in his office","firstSeen":"2026-04-12T16:56:05.188Z","peakCount":65935,"prevCount":65935,"velocity":-100,"status":"gone"},{"url":"/weibo?q=%23%E5%A5%B3%E5%BD%93%E4%BA%8B%E4%BA%BA%E5%9B%9E%E5%BA%94%E8%A2%AB%E6%B3%95%E5%AE%98%E7%8C%A5%E4%BA%B5%23","text":"女当事人回应被法官猥亵","count":65901,"firstSeen":"2026-04-12T18:23:51.235Z","peakCount":65901,"prevCount":65901,"velocity":-100,"status":"gone"},{"url":"/weibo?q=%23%E4%BC%8A%E6%9C%97%E6%8E%A5%E8%BF%9E%E5%9B%9E%E6%80%BC%E7%BE%8E%E5%9B%BD%23","text":"伊朗接连回怼美国","count":65725,"textEn":"Iran attacks the United States one after another","firstSeen":"2026-04-12T16:05:16.357Z","peakCount":66777,"prevCount":65725,"velocity":-100,"status":"gone"},{"url":"/weibo?q=%23%E6%9F%B3%E8%87%B4%E6%95%8F%23","text":"柳致敏","count":65528,"textEn":"Liu Zhimin","firstSeen":"2026-04-12T16:05:16.357Z","peakCount":138515,"prevCount":65528,"velocity":-100,"status":"gone"},{"url":"/weibo?q=%23%E8%BF%AA%E4%B8%BD%E7%83%AD%E5%B7%B4%E8%A1%A5%E5%81%BF%E5%8E%BB%E5%B7%B4%E9%BB%8E%E7%9A%84%E7%B2%89%E4%B8%9D%23","text":"迪丽热巴补偿去巴黎的粉丝","count":65277,"firstSeen":"2026-04-12T16:05:16.357Z","peakCount":92887,"prevCount":65277,"velocity":-100,"status":"gone","textEn":"Dilireba compensates fans who went to Paris"},{"url":"/weibo?q=%23%E4%BC%8A%E6%96%B9%E8%AF%B4%E5%B0%81%E9%94%81%E4%BC%8A%E6%9C%97%E6%97%A0%E6%B3%95%E8%AE%A9%E9%9C%8D%E5%B0%94%E6%9C%A8%E5%85%B9%E6%B5%B7%E5%B3%A1%E5%BC%80%E6%94%BE%23","text":"伊方说封锁伊朗无法让霍尔木兹海峡开放","count":65208,"textEn":"Iran says blocking Iran will not allow Strait of Hormuz to open","firstSeen":"2026-04-12T16:05:16.357Z","peakCount":95459,"prevCount":65208,"velocity":-100,"status":"gone"},{"url":"/weibo?q=%23%E8%84%91%E9%9B%BE%E5%88%B0%E5%BA%95%E6%98%AF%E4%B8%AA%E5%95%A5%23","text":"脑雾到底是个啥","count":64942,"textEn":"What exactly is brain fog?","firstSeen":"2026-04-12T16:56:05.188Z","peakCount":64942,"prevCount":64942,"velocity":-100,"status":"gone"},{"url":"/weibo?q=%23%E6%A5%9A%E4%B9%94%E4%BC%A0%20%E7%9F%A5%E5%90%A6%23","text":"楚乔传 知否","count":64758,"firstSeen":"2026-04-12T16:05:16.357Z","peakCount":129175,"prevCount":64758,"velocity":-100,"status":"gone"},{"url":"/weibo?q=%23%E6%99%AE%E4%BA%AC%E5%92%8C%E4%BC%8A%E6%9C%97%E6%80%BB%E7%BB%9F%E9%80%9A%E8%AF%9D%23","text":"普京和伊朗总统通话","count":64750,"textEn":"Putin talks to Iranian president","firstSeen":"2026-04-12T16:56:05.188Z","peakCount":64750,"prevCount":64750,"velocity":-100,"status":"gone"},{"url":"/weibo?q=%23%E8%A5%BF%E7%8F%AD%E7%89%99%E9%A6%96%E7%9B%B8%E9%80%9B%E5%AE%8C%E9%BC%93%E6%A5%BC%E9%80%9B%E9%A2%90%E5%92%8C%E5%9B%AD%23","text":"西班牙首相逛完鼓楼逛颐和园","count":64333,"firstSeen":"2026-04-12T20:34:16.727Z","peakCount":64333,"prevCount":64333,"velocity":-100,"status":"gone"},{"url":"/weibo?q=%23%E5%B1%B1%E8%A5%BF%E4%B8%80%E6%B3%95%E5%AE%98%E7%8C%A5%E4%BA%B5%E5%BD%93%E4%BA%8B%E4%BA%BA%E7%BA%AA%E6%A3%80%E9%83%A8%E9%97%A8%E4%BB%8B%E5%85%A5%23","text":"山西一法官猥亵当事人纪检部门介入","count":64091,"firstSeen":"2026-04-12T19:12:49.278Z","peakCount":64091,"prevCount":64091,"velocity":-100,"status":"gone"},{"url":"/weibo?q=%23%E6%B5%AA%E5%A7%90%23","text":"浪姐","count":63974,"firstSeen":"2026-04-12T17:38:37.862Z","peakCount":63974,"prevCount":63974,"velocity":-100,"status":"gone"},{"url":"/weibo?q=%23%E9%98%BF%E5%B0%94%E5%8D%A1%E6%8B%89%E6%96%AFvs%E8%BE%9B%E7%BA%B3%23","text":"阿尔卡拉斯vs辛纳","count":63847,"textEn":"Alcaraz vs Sinner","firstSeen":"2026-04-12T16:05:16.357Z","peakCount":149786,"prevCount":63847,"velocity":-100,"status":"gone"},{"url":"/weibo?q=%23%E6%B5%AA%E5%A7%90%E4%BA%8C%E5%85%AC%E5%88%86%E7%BB%84%E6%9B%B2%E7%9B%AE%23","text":"浪姐二公分组曲目","count":63668,"firstSeen":"2026-04-12T16:05:16.357Z","peakCount":97146,"prevCount":63668,"velocity":-100,"status":"gone"},{"url":"/weibo?q=%23%E8%BE%9B%E7%BA%B3%E9%A6%96%E5%A4%BA%E8%92%99%E7%89%B9%E5%8D%A1%E6%B4%9B%E5%86%A0%E5%86%9B%23","text":"辛纳首夺蒙特卡洛冠军","count":63550,"firstSeen":"2026-04-12T16:05:16.357Z","peakCount":88409,"prevCount":63550,"velocity":-100,"status":"gone"},{"url":"/weibo?q=%23%E7%8E%8B%E6%A9%B9%E6%9D%B0%E7%94%BB%E7%9A%84%E5%B0%8F%E5%B0%8F%E5%92%B4%23","text":"王橹杰画的小小咴","count":63396,"textEn":"The little cock drawn by Wang Lujie","firstSeen":"2026-04-12T19:12:49.278Z","peakCount":63396,"prevCount":63396,"velocity":-100,"status":"gone"},{"url":"/weibo?q=%23TTG%E5%AF%B9%E6%88%98KSG%23","text":"TTG对战KSG","count":63230,"textEn":"TTG vs. KSG","firstSeen":"2026-04-12T16:05:16.357Z","peakCount":63230,"prevCount":63230,"velocity":-100,"status":"gone"}]